<Emitter name="RockSpike">
	<Emission emissionRate="1.0" emissionRadius="1.00" boxDimensions="0.700,0.700,0.200" lifetime="3.00, 3.00" emissionType="1" meshFilePath="" meshScale="1.000,1.000,1.000" emissionMode="1" repeat="0" repeatTime="1.00" emitTime="-1.00" numBursts="1" burstInterval="0.100"/>
	<Physics ignoreWorldPhysics="1" depthBufferCollisions="0" velocityXRange="0.00,0.00" velocityYRange="0.00,0.00" velocityZRange="0.00,0.00" inheritEmitterVelocity="0" inheritVelocityPercentage="1.00" setLifetimeVelocity="1" velocityMode="0" orientToVelocity="0" perlinNoiseForce="0.00"
	curlNoiseAffectPosition="0" curlNoiseScale="10.00" curlNoiseSampleSize="10.00" curlNoiseOctives="1" curlNoisePan="0.00, 0.00, 0.00"
	pointForcePosition="0.00,0.00,0.00" pointForceFalloffExponent="2.00" pointForceAttract="true" pointForceRadius="0.00"
	returnToOriginForce="0.00" returnToOriginDelay="1.00" ignoreForcesWhenAtOrigin="0"
	vortexAxisDir="1.00,0.00,0.00" vortexAxisOrigin="0.00,0.00,0.00" vortexForceRadius="0.00">
	</Physics>
	<Appearance spriteSheetFilePath="Data/Images/RocksAlbedo.png" spriteSheetDimensions="1,1" spriteStartIndex="0" spriteEndIndex="0" stretchBillboard="0" lengthPerSpeed="0.00" spriteEasingFunction="0" stretchMode="0" renderMode="1" particleMeshFilePath="Data/Models/RockSpike.xml" partialMeshTriangles="0">
		<ColorOverLife color="255,255,255,255" time="0.00"/>
		<ColorOverLife color="255,255,255,255" time="0.90"/>
		<ColorOverLife color="255,255,255,0" time="1.00"/>
		<PanTexture textureToPan="" panTextureSampleScale="1.00,1.00" panTextureSpeed="0.00,0.00"/>
	</Appearance>
<FloatGraphs>
	<FloatGraph floatGraphType="0" constantValue="10.000" dataMode="0" minValue="10.000" maxValue="10.000">
		<FloatPoint minValue="10.000" maxValue="10.000" time="0.000" easingFunction="0"/>
	</FloatGraph>
	<FloatGraph floatGraphType="1" constantValue="0.000" dataMode="0" minValue="0.000" maxValue="0.000">
		<FloatPoint minValue="0.000" maxValue="0.000" time="0.000" easingFunction="0"/>
	</FloatGraph>
	<FloatGraph floatGraphType="2" constantValue="0.000" dataMode="0" minValue="0.000" maxValue="0.000">
		<FloatPoint minValue="0.000" maxValue="0.000" time="0.000" easingFunction="0"/>
	</FloatGraph>
	<FloatGraph floatGraphType="3" constantValue="0.000" dataMode="0" minValue="0.000" maxValue="0.000">
		<FloatPoint minValue="0.000" maxValue="0.000" time="0.000" easingFunction="0"/>
	</FloatGraph>
	<FloatGraph floatGraphType="4" constantValue="0.000" dataMode="0" minValue="0.000" maxValue="0.000">
		<FloatPoint minValue="0.000" maxValue="0.000" time="0.000" easingFunction="0"/>
	</FloatGraph>
	<FloatGraph floatGraphType="5" constantValue="2.000" dataMode="0" minValue="0.000" maxValue="0.000">
		<FloatPoint minValue="0.000" maxValue="0.000" time="0.000" easingFunction="0"/>
	</FloatGraph>
	<FloatGraph floatGraphType="6" constantValue="1.000" dataMode="0" minValue="1.000" maxValue="1.000">
		<FloatPoint minValue="1.000" maxValue="1.000" time="0.000" easingFunction="0"/>
	</FloatGraph>
	<FloatGraph floatGraphType="7" constantValue="0.000" dataMode="0" minValue="0.000" maxValue="0.000">
		<FloatPoint minValue="0.000" maxValue="0.000" time="0.000" easingFunction="0"/>
	</FloatGraph>
	<FloatGraph floatGraphType="8" constantValue="0.000" dataMode="0" minValue="0.000" maxValue="0.000">
		<FloatPoint minValue="0.000" maxValue="0.000" time="0.000" easingFunction="0"/>
	</FloatGraph>
	<FloatGraph floatGraphType="9" constantValue="0.000" dataMode="0" minValue="0.000" maxValue="0.000">
		<FloatPoint minValue="0.000" maxValue="0.000" time="0.000" easingFunction="0"/>
	</FloatGraph>
</FloatGraphs>
<Float2Graphs>
	<Float2Graph float2GraphType="0" constantValue="1.000, 1.000" dataMode="0" minValue="1.000, 1.000" maxValue="1.000, 1.000">
		<Float2Point minValue="1.000,1.000" maxValue="1.000,1.000" time="0.000" easingFunction="0"/>
	</Float2Graph>
</Float2Graphs>
<Float3Graphs>
	<Float3Graph float3GraphType="0" constantValue="0.000,0.000,0.000" dataMode="0" minValue="0.000,0.000,10.000" maxValue="0.000,0.000,10.000">
		<Float3Point minValue="0.000,0.000,10.000" maxValue="0.000,0.000,10.000" time="0.000" easingFunction="0"/>
	</Float3Graph>
	<Float3Graph float3GraphType="1" constantValue="0.000,0.000,10.000" dataMode="2" minValue="0.000,0.000,10.000" maxValue="0.000,0.000,10.000">
		<Float3Point minValue="0.000,0.000,10.000" maxValue="0.000,0.000,10.000" time="0.000" easingFunction="6"/>
		<Float3Point minValue="0.000,0.000,-2.000" maxValue="0.000,0.000,-2.000" time="0.100" easingFunction="12"/>
		<Float3Point minValue="0.000,0.000,0.000" maxValue="0.000,0.000,0.000" time="0.120" easingFunction="0"/>
	</Float3Graph>
	<Float3Graph float3GraphType="2" constantValue="0.000,0.000,0.000" dataMode="2" minValue="0.000,0.000,0.000" maxValue="0.000,0.000,0.000">
		<Float3Point minValue="0.000,0.000,-2.000" maxValue="0.000,0.000,-2.000" time="0.000" easingFunction="7"/>
		<Float3Point minValue="0.000,0.000,0.000" maxValue="0.000,0.000,0.000" time="0.075" easingFunction="0"/>
	</Float3Graph>
	<Float3Graph float3GraphType="3" constantValue="0.000,0.000,0.000" dataMode="1" minValue="-45.000,0.000,0.000" maxValue="45.000,0.000,0.000">
		<Float3Point minValue="0.000,0.000,0.000" maxValue="0.000,0.000,0.000" time="0.000" easingFunction="0"/>
	</Float3Graph>
	<Float3Graph float3GraphType="4" constantValue="1.000,1.000,1.000" dataMode="2" minValue="1.000,1.000,1.000" maxValue="1.500,1.500,1.500">
		<Float3Point minValue="0.250,0.250,0.250" maxValue="0.350,0.350,0.350" time="0.000" easingFunction="6"/>
		<Float3Point minValue="1.250,1.250,1.250" maxValue="2.000,2.000,2.000" time="0.100" easingFunction="0"/>
	</Float3Graph>
</Float3Graphs>
<EmitterProperties lifetime="-1.00" startDelay="-1.00" worldSimulation="1" emitEmitters="0" subEmitterFilePath="" minSubEmitterOrientation="0.00,0.00,0.00" maxSubEmitterOrientation="0.00,0.00,0.00">
	<EmitterVelocity constantValue="0.000,0.000,0.000" dataMode="0" minValue="0.000,0.000,0.000" maxValue="0.000,0.000,0.000">
		<Float3Point minValue="5.000,-2.500,0.000" maxValue="5.000,-2.500,0.000" time="0.000" easingFunction="11"/>
		<Float3Point minValue="5.000,2.500,0.000" maxValue="5.000,2.500,0.000" time="0.250" easingFunction="0"/>
		<Float3Point minValue="5.000,-2.500,0.000" maxValue="5.000,-2.500,0.000" time="0.500" easingFunction="0"/>
		<Float3Point minValue="5.000,2.500,0.000" maxValue="5.000,2.500,0.000" time="0.750" easingFunction="0"/>
		<Float3Point minValue="5.000,-2.500,0.000" maxValue="5.000,-2.500,0.000" time="1.000" easingFunction="0"/>
	</EmitterVelocity>
	<EmitterChildren>
		<EmitterChild fileName="Data/Saves/ParticleEmitters/RockDustEmitter.xml" position="0.000,0.000,1.500" orientation="0.000,0.000,0.000"/>
		<EmitterChild fileName="Data/Saves/ParticleEmitters/RockDebrisEmitter.xml" position="0.000,0.000,1.500" orientation="0.000,0.000,0.000"/>
	</EmitterChildren>
</EmitterProperties>
</Emitter>
